{"metadata":{"timestamp":"2025-01-12T02:02:53Z"},"serialNumber":"urn:uuid:49cf8388-4314-438a-991e-05fb280e96ba","components":[{"version":"2024.12.22","licenses":[{"license":{"name":"AGPL-3.0-only"}}],"name":"chinadns-ng","type":"application"},{"version":"0.9.0","licenses":[{"license":{"name":"AGPL-3.0-only"}}],"name":"dae","type":"application"},{"type":"application","name":"dae-geoip","licenses":[{"license":{"name":"AGPL-3.0-only"}}],"version":"0.9.0"},{"licenses":[{"license":{"name":"AGPL-3.0-only"}}],"version":"0.9.0","type":"application","name":"dae-geosite"},{"licenses":[{"license":{"name":"AGPL-3.0-only"}},{"license":{"name":"MIT"}}],"version":"0.9.0","type":"application","name":"daed"},{"type":"application","name":"dns2socks","licenses":[{"license":{"name":"BSD-3-Clause"}}],"version":"2.1"},{"name":"dns2tcp","type":"application","version":"1.1.2","licenses":[{"license":{"name":"AGPL-3.0-only"}}]},{"type":"application","name":"geoview","licenses":[{"license":{"name":"Apache-2.0"}}],"version":"0.1.0"},{"type":"application","cpe":"cpe:/a:haproxy:haproxy:3.0.7","name":"halog","licenses":[{"license":{"name":"GPL-2.0-only"}}],"version":"3.0.7"},{"cpe":"cpe:/a:haproxy:haproxy:3.0.7","type":"application","name":"haproxy","licenses":[{"license":{"name":"GPL-2.0-only"}}],"version":"3.0.7"},{"version":"3.0.7","licenses":[{"license":{"name":"GPL-2.0-only"}}],"name":"haproxy-nossl","type":"application","cpe":"cpe:/a:haproxy:haproxy:3.0.7"},{"licenses":[{"license":{"name":"MIT"}}],"version":"2.6.0","type":"application","name":"hysteria"},{"name":"ipt2socks","type":"application","version":"1.1.4","licenses":[{"license":{"name":"AGPL-3.0"}}]},{"licenses":[{"license":{"name":"MIT"}}],"version":"1.1-1","type":"application","name":"lua-neturl"},{"name":"luci-app-dae","type":"application","version":"git-25.012.02452-1e237df","licenses":[{"license":{"name":"Apache-2.0"}}]},{"name":"luci-app-daed","type":"application","version":"git-25.012.02452-1e237df"},{"version":"git-25.012.02452-1e237df","name":"luci-app-homeproxy","type":"application"},{"name":"luci-app-mihomo","type":"application","version":"1.17.3"},{"version":"0.46.064","name":"luci-app-openclash","type":"application"},{"version":"25.1.8","type":"application","name":"luci-app-passwall"},{"type":"application","name":"luci-app-passwall2","version":"25.1.8"},{"version":"189","type":"application","name":"luci-app-ssr-plus"},{"type":"application","name":"luci-i18n-dae-zh-cn","licenses":[{"license":{"name":"Apache-2.0"}}],"version":"git-25.012.02452-1e237df"},{"name":"luci-i18n-daed-zh-cn","type":"application","version":"git-25.012.02452-1e237df"},{"version":"git-25.012.02452-1e237df","type":"application","name":"luci-i18n-homeproxy-zh-cn"},{"type":"application","name":"luci-i18n-mihomo-zh-cn","version":"git-25.012.02452-1e237df"},{"version":"git-25.012.02452-1e237df","name":"luci-i18n-passwall-zh-cn","type":"application"},{"version":"git-25.012.02452-1e237df","name":"luci-i18n-passwall2-zh-cn","type":"application"},{"version":"git-25.012.02452-1e237df","name":"luci-i18n-ssr-plus-zh-cn","type":"application"},{"version":"1.0.4","licenses":[{"license":{"name":"MIT"}}],"name":"microsocks","type":"application"},{"licenses":[{"license":{"name":"MIT"}}],"version":"2025-01-07-c7661d77","type":"application","name":"mihomo"},{"type":"application","name":"naiveproxy","licenses":[{"license":{"name":"BSD"}},{"license":{"name":"3-Clause"}}],"version":"131.0.6778.86"},{"version":"1.2.9b-par","type":"application","name":"pdnsd-alt"},{"licenses":[{"license":{"name":"Apache-2.0"}}],"version":"0.71","type":"application","name":"redsocks2"},{"type":"application","name":"shadow-tls","version":"0.2.25"},{"version":"3.3.5","licenses":[{"license":{"name":"GPL-3.0-or-later"}}],"name":"shadowsocks-libev-config","type":"application","cpe":"cpe:/a:shadowsocks:shadowsocks-libev:3.3.5"},{"licenses":[{"license":{"name":"GPL-3.0-or-later"}}],"version":"3.3.5","type":"application","cpe":"cpe:/a:shadowsocks:shadowsocks-libev:3.3.5","name":"shadowsocks-libev-ss-local"},{"version":"3.3.5","licenses":[{"license":{"name":"GPL-3.0-or-later"}}],"name":"shadowsocks-libev-ss-redir","cpe":"cpe:/a:shadowsocks:shadowsocks-libev:3.3.5","type":"application"},{"cpe":"cpe:/a:shadowsocks:shadowsocks-libev:3.3.5","type":"application","name":"shadowsocks-libev-ss-rules","licenses":[{"license":{"name":"GPL-3.0-or-later"}}],"version":"3.3.5"},{"name":"shadowsocks-libev-ss-server","type":"application","cpe":"cpe:/a:shadowsocks:shadowsocks-libev:3.3.5","version":"3.3.5","licenses":[{"license":{"name":"GPL-3.0-or-later"}}]},{"licenses":[{"license":{"name":"GPL-3.0-or-later"}}],"version":"3.3.5","cpe":"cpe:/a:shadowsocks:shadowsocks-libev:3.3.5","type":"application","name":"shadowsocks-libev-ss-tunnel"},{"licenses":[{"license":{"name":"MIT"}}],"version":"1.22.0","type":"application","name":"shadowsocks-rust-sslocal"},{"version":"1.22.0","licenses":[{"license":{"name":"MIT"}}],"name":"shadowsocks-rust-ssmanager","type":"application"},{"version":"1.22.0","licenses":[{"license":{"name":"MIT"}}],"name":"shadowsocks-rust-ssserver","type":"application"},{"name":"shadowsocks-rust-ssservice","type":"application","version":"1.22.0","licenses":[{"license":{"name":"MIT"}}]},{"type":"application","name":"shadowsocks-rust-ssurl","licenses":[{"license":{"name":"MIT"}}],"version":"1.22.0"},{"version":"2.5.6","licenses":[{"license":{"name":"GPL-3.0"}}],"name":"shadowsocksr-libev-ssr-check","type":"application"},{"type":"application","name":"shadowsocksr-libev-ssr-local","licenses":[{"license":{"name":"GPL-3.0"}}],"version":"2.5.6"},{"name":"shadowsocksr-libev-ssr-nat","type":"application","version":"2.5.6","licenses":[{"license":{"name":"GPL-3.0"}}]},{"type":"application","name":"shadowsocksr-libev-ssr-redir","licenses":[{"license":{"name":"GPL-3.0"}}],"version":"2.5.6"},{"version":"2.5.6","licenses":[{"license":{"name":"GPL-3.0"}}],"name":"shadowsocksr-libev-ssr-server","type":"application"},{"name":"simple-obfs-client","type":"application","version":"0.0.5","licenses":[{"license":{"name":"GPL-3.0-or-later"}}]},{"licenses":[{"license":{"name":"GPL-3.0-or-later"}}],"version":"0.0.5","type":"application","name":"simple-obfs-server"},{"licenses":[{"license":{"name":"GPL-3.0-or-later"}}],"version":"1.10.6","type":"application","name":"sing-box"},{"licenses":[{"license":{"name":"GPL-2.0-only"}}],"version":"0.3","type":"application","name":"tcping"},{"licenses":[{"license":{"name":"GPL-3.0"}}],"version":"1.16.0","type":"application","name":"trojan"},{"licenses":[{"license":{"name":"GPL-3.0"}}],"version":"10.0.3","type":"application","name":"trojan-plus"},{"version":"1.0.0","name":"tuic-client","type":"application"},{"type":"application","name":"v2ray-core","licenses":[{"license":{"name":"MIT"}}],"version":"5.24.0"},{"version":"5.24.0","licenses":[{"license":{"name":"MIT"}}],"name":"v2ray-extra","type":"application"},{"type":"application","name":"v2ray-geoip","licenses":[{"license":{"name":"CC-BY-SA-4.0"}}],"version":"20250112241031"},{"licenses":[{"license":{"name":"GPL-3.0"}}],"version":"20250112241031","type":"application","name":"v2ray-geosite"},{"version":"5.17.0","licenses":[{"license":{"name":"MIT"}}],"name":"v2ray-plugin","type":"application"},{"version":"24.12.31","licenses":[{"license":{"name":"MPL-2.0"}}],"name":"xray-core","type":"application"},{"licenses":[{"license":{"name":"MIT"}}],"version":"1.8.24","type":"application","name":"xray-plugin"}],"bomFormat":"CycloneDX","specVersion":"1.4","version":1}